<?xml version="1.0" encoding="utf-8" ?><dwsync><file name="icon_youtube.svg" server="wp-demo.hosting.cornell.edu" local="3703676859" remote="3703676859" Dst="-1" /><file name="checked.svg" server="wp-demo.hosting.cornell.edu" local="3703676859" remote="3703676859" Dst="-1" /><file name="icon_phone.svg" server="wp-demo.hosting.cornell.edu" local="3703676859" remote="3703676859" Dst="-1" /><file name="icon_globe.svg" server="wp-demo.hosting.cornell.edu" local="3703676859" remote="3703676859" Dst="-1" /><file name="unfold-more.svg" server="wp-demo.hosting.cornell.edu" local="3703676860" remote="3703676860" Dst="-1" /><file name="icon_instagram.svg" server="wp-demo.hosting.cornell.edu" local="3703676860" remote="3703676860" Dst="-1" /><file name="clocktower.svg" server="wp-demo.hosting.cornell.edu" local="3703676860" remote="3703676860" Dst="-1" /><file name="unfold-less.svg" server="wp-demo.hosting.cornell.edu" local="3703676860" remote="3703676860" Dst="-1" /><file name="flourish1.svg" server="wp-demo.hosting.cornell.edu" local="3703676861" remote="3703676861" Dst="-1" /><file name="icon_search.svg" server="wp-demo.hosting.cornell.edu" local="3703676861" remote="3703676861" Dst="-1" /><file name="unfold-band-blue.svg" server="wp-demo.hosting.cornell.edu" local="3703676861" remote="3703676861" Dst="-1" /><file name="icon_twitter.svg" server="wp-demo.hosting.cornell.edu" local="3703676861" remote="3703676861" Dst="-1" /><file name="sidebar_top_fade.png" server="wp-demo.hosting.cornell.edu" local="3703676861" remote="3703676861" Dst="-1" /><file name="icon_facebook.svg" server="wp-demo.hosting.cornell.edu" local="3703676862" remote="3703676862" Dst="-1" /><file name="icon_lock.svg" server="wp-demo.hosting.cornell.edu" local="3703676862" remote="3703676862" Dst="-1" /><file name="icon_mail_fade.svg" server="wp-demo.hosting.cornell.edu" local="3703676862" remote="3703676862" Dst="-1" /><file name="icon_mail.svg" server="wp-demo.hosting.cornell.edu" local="3703676863" remote="3703676863" Dst="-1" /><file name="checked-radio.svg" server="wp-demo.hosting.cornell.edu" local="3703676863" remote="3703676863" Dst="-1" /><file name="icon_phone_fade.svg" server="wp-demo.hosting.cornell.edu" local="3703676863" remote="3703676863" Dst="-1" /><file name="unfold-band-defaultblue.svg" server="wp-demo.hosting.cornell.edu" local="3703676863" remote="3703676863" Dst="-1" /><file name="unfold-band.svg" server="wp-demo.hosting.cornell.edu" local="3703676863" remote="3703676863" Dst="-1" /><file name="icon_lock_fade.svg" server="wp-demo.hosting.cornell.edu" local="3703676864" remote="3703676864" Dst="-1" /><file name="icon_linkedin.svg" server="wp-demo.hosting.cornell.edu" local="3703676864" remote="3703676864" Dst="-1" /><file name="icon_search_fade.svg" server="wp-demo.hosting.cornell.edu" local="3703676864" remote="3703676864" Dst="-1" /><file name="icon_globe_fade.svg" server="wp-demo.hosting.cornell.edu" local="3703676865" remote="3703676865" Dst="-1" /></dwsync>