<?xml version="1.0" encoding="utf-8" ?><dwsync><file name="cornell-custom.woff" server="wp-demo.hosting.cornell.edu" local="3703676915" remote="3703676915" Dst="-1" /><file name="fontawesome-webfont.svg" server="wp-demo.hosting.cornell.edu" local="3703676917" remote="3703676917" Dst="-1" /><file name="cornell-custom.eot" server="wp-demo.hosting.cornell.edu" local="3703676917" remote="3703676917" Dst="-1" /><file name="Material-Design-Iconic-Font.eot" server="wp-demo.hosting.cornell.edu" local="3703676917" remote="3703676917" Dst="-1" /><file name="FontAwesome.otf" server="wp-demo.hosting.cornell.edu" local="3703676918" remote="3703676918" Dst="-1" /><file name="totally-cornered.eot" server="wp-demo.hosting.cornell.edu" local="3703676918" remote="3703676918" Dst="-1" /><file name="service-logos.css" server="wp-demo.hosting.cornell.edu" local="3703676918" remote="3703676918" Dst="-1" /><file name="cornell-custom.ttf" server="wp-demo.hosting.cornell.edu" local="3703676918" remote="3703676918" Dst="-1" /><file name="totally-cornered.ttf" server="wp-demo.hosting.cornell.edu" local="3703676919" remote="3703676919" Dst="-1" /><file name="Material-Design-Iconic-Font.ttf" server="wp-demo.hosting.cornell.edu" local="3703676919" remote="3703676919" Dst="-1" /><file name="totally-cornered.woff" server="wp-demo.hosting.cornell.edu" local="3703676919" remote="3703676919" Dst="-1" /><file name="service-logos.svg" server="wp-demo.hosting.cornell.edu" local="3703676919" remote="3703676919" Dst="-1" /><file name="fontawesome-webfont.woff2" server="wp-demo.hosting.cornell.edu" local="3703676920" remote="3703676920" Dst="-1" /><file name="service-logos.woff" server="wp-demo.hosting.cornell.edu" local="3703676920" remote="3703676920" Dst="-1" /><file name="service-logos.eot" server="wp-demo.hosting.cornell.edu" local="3703676920" remote="3703676920" Dst="-1" /><file name="Material-Design-Iconic-Font.woff" server="wp-demo.hosting.cornell.edu" local="3703676920" remote="3703676920" Dst="-1" /><file name="Material-Design-Iconic-Font.woff2" server="wp-demo.hosting.cornell.edu" local="3703676920" remote="3703676920" Dst="-1" /><file name="fontawesome-webfont.ttf" server="wp-demo.hosting.cornell.edu" local="3703676921" remote="3703676921" Dst="-1" /><file name="font-awesome.min.css" server="wp-demo.hosting.cornell.edu" local="3703676921" remote="3703676921" Dst="-1" /><file name="material-design-iconic-font.min.css" server="wp-demo.hosting.cornell.edu" local="3703676921" remote="3703676921" Dst="-1" /><file name="fontawesome-webfont.woff" server="wp-demo.hosting.cornell.edu" local="3703676921" remote="3703676921" Dst="-1" /><file name="totally-cornered.css" server="wp-demo.hosting.cornell.edu" local="3703676922" remote="3703676922" Dst="-1" /><file name="cornell-custom.css" server="wp-demo.hosting.cornell.edu" local="3703676922" remote="3703676922" Dst="-1" /><file name="service-logos.ttf" server="wp-demo.hosting.cornell.edu" local="3703676922" remote="3703676922" Dst="-1" /><file name="fontawesome-webfont.eot" server="wp-demo.hosting.cornell.edu" local="3703676922" remote="3703676922" Dst="-1" /><file name="cornell-custom.svg" server="wp-demo.hosting.cornell.edu" local="3703676923" remote="3703676923" Dst="-1" /><file name="totally-cornered.svg" server="wp-demo.hosting.cornell.edu" local="3703676923" remote="3703676923" Dst="-1" /><file name="Material-Design-Iconic-Font.svg" server="wp-demo.hosting.cornell.edu" local="3703676923" remote="3703676923" Dst="-1" /></dwsync>